{
  "accentColor": "{{appsmith.theme.colors.primaryColor}}",
  "animateLoading": true,
  "borderColor": "#E0DEDE",
  "borderRadius": "{{appsmith.theme.borderRadius.appBorderRadius}}",
  "borderWidth": "1",
  "bottomRow": 78,
  "boxShadow": "{{appsmith.theme.boxShadow.appBoxShadow}}",
  "canFreezeColumn": true,
  "childStylesheet": {
    "button": {
      "borderRadius": "{{appsmith.theme.borderRadius.appBorderRadius}}",
      "boxShadow": "none",
      "buttonColor": "{{appsmith.theme.colors.primaryColor}}"
    },
    "editActions": {
      "discardBorderRadius": "{{appsmith.theme.borderRadius.appBorderRadius}}",
      "discardButtonColor": "{{appsmith.theme.colors.primaryColor}}",
      "saveBorderRadius": "{{appsmith.theme.borderRadius.appBorderRadius}}",
      "saveButtonColor": "{{appsmith.theme.colors.primaryColor}}"
    },
    "iconButton": {
      "borderRadius": "{{appsmith.theme.borderRadius.appBorderRadius}}",
      "boxShadow": "none",
      "buttonColor": "{{appsmith.theme.colors.primaryColor}}"
    },
    "menuButton": {
      "borderRadius": "{{appsmith.theme.borderRadius.appBorderRadius}}",
      "boxShadow": "none",
      "menuColor": "{{appsmith.theme.colors.primaryColor}}"
    }
  },
  "columnOrder": [
    "Category",
    "Description",
    "Quantity_Nos",
    "Cost_INR",
    "Remarks"
  ],
  "columnUpdatedAt": 1739256569159,
  "columnWidthMap": {},
  "customIsLoading": false,
  "customIsLoadingValue": "",
  "defaultPageSize": 0,
  "defaultSelectedRowIndex": 0,
  "defaultSelectedRowIndices": [
    0
  ],
  "delimiter": ",",
  "dynamicBindingPathList": [
    {
      "key": "accentColor"
    },
    {
      "key": "borderRadius"
    },
    {
      "key": "boxShadow"
    },
    {
      "key": "tableData"
    },
    {
      "key": "primaryColumns.Quantity_Nos.computedValue"
    },
    {
      "key": "primaryColumns.Description.computedValue"
    },
    {
      "key": "primaryColumns.Category.computedValue"
    },
    {
      "key": "primaryColumns.Cost_INR.computedValue"
    },
    {
      "key": "primaryColumns.Remarks.computedValue"
    }
  ],
  "dynamicPropertyPathList": [
    {
      "key": "tableData"
    }
  ],
  "dynamicTriggerPathList": [],
  "enableClientSideSearch": true,
  "flexVerticalAlignment": "start",
  "horizontalAlignment": "LEFT",
  "inlineEditingSaveOption": "ROW_LEVEL",
  "isLoading": false,
  "isSortable": true,
  "isVisible": true,
  "isVisibleDownload": true,
  "isVisibleFilters": false,
  "isVisiblePagination": true,
  "isVisibleSearch": true,
  "key": "nf93e9z6d8",
  "label": "Data",
  "leftColumn": 2,
  "minWidth": 450,
  "mobileBottomRow": 70,
  "mobileLeftColumn": 2,
  "mobileRightColumn": 36,
  "mobileTopRow": 42,
  "needsErrorInfo": false,
  "parentColumnSpace": 13.53125,
  "parentId": "0",
  "parentRowSpace": 10,
  "primaryColumns": {
    "Category": {
      "alias": "Category",
      "allowCellWrapping": false,
      "allowSameOptionsInNewRow": true,
      "columnType": "text",
      "computedValue": "{{(() => { const tableData = Table1.processedTableData || []; return tableData.length > 0 ? tableData.map((currentRow, currentIndex) => ( currentRow[\"Category\"])) :  currentRow[\"Category\"] })()}}",
      "currencyCode": "USD",
      "decimals": 0,
      "enableFilter": true,
      "enableSort": true,
      "horizontalAlignment": "CENTER",
      "id": "Category",
      "index": 2,
      "isCellEditable": false,
      "isCellVisible": true,
      "isDerived": false,
      "isDisabled": false,
      "isDiscardVisible": true,
      "isEditable": false,
      "isSaveVisible": true,
      "isVisible": true,
      "label": "Category",
      "notation": "standard",
      "originalId": "Category",
      "sticky": "",
      "textSize": "0.875rem",
      "thousandSeparator": true,
      "validation": {},
      "verticalAlignment": "CENTER",
      "width": 150
    },
    "Cost_INR": {
      "alias": "Cost_INR",
      "allowCellWrapping": false,
      "allowSameOptionsInNewRow": true,
      "columnType": "number",
      "computedValue": "{{(() => { const tableData = Table1.processedTableData || []; return tableData.length > 0 ? tableData.map((currentRow, currentIndex) => ( currentRow[\"Cost_INR\"])) :  currentRow[\"Cost_INR\"] })()}}",
      "currencyCode": "USD",
      "decimals": 0,
      "enableFilter": true,
      "enableSort": true,
      "horizontalAlignment": "RIGHT",
      "id": "Cost_INR",
      "index": 3,
      "isCellEditable": false,
      "isCellVisible": true,
      "isDerived": false,
      "isDisabled": false,
      "isDiscardVisible": true,
      "isEditable": false,
      "isSaveVisible": true,
      "isVisible": true,
      "label": "Cost_INR",
      "notation": "standard",
      "originalId": "Cost_INR",
      "sticky": "",
      "textSize": "0.875rem",
      "thousandSeparator": true,
      "validation": {},
      "verticalAlignment": "CENTER",
      "width": 150
    },
    "Description": {
      "alias": "Description",
      "allowCellWrapping": false,
      "allowSameOptionsInNewRow": true,
      "columnType": "text",
      "computedValue": "{{(() => { const tableData = Table1.processedTableData || []; return tableData.length > 0 ? tableData.map((currentRow, currentIndex) => ( currentRow[\"Description\"])) :  currentRow[\"Description\"] })()}}",
      "currencyCode": "USD",
      "decimals": 0,
      "enableFilter": true,
      "enableSort": true,
      "horizontalAlignment": "CENTER",
      "id": "Description",
      "index": 1,
      "isCellEditable": false,
      "isCellVisible": true,
      "isDerived": false,
      "isDisabled": false,
      "isDiscardVisible": true,
      "isEditable": false,
      "isSaveVisible": true,
      "isVisible": true,
      "label": "Description",
      "notation": "standard",
      "originalId": "Description",
      "sticky": "",
      "textSize": "0.875rem",
      "thousandSeparator": true,
      "validation": {},
      "verticalAlignment": "CENTER",
      "width": 150
    },
    "Quantity_Nos": {
      "alias": "Quantity_Nos",
      "allowCellWrapping": false,
      "allowSameOptionsInNewRow": true,
      "columnType": "number",
      "computedValue": "{{(() => { const tableData = Table1.processedTableData || []; return tableData.length > 0 ? tableData.map((currentRow, currentIndex) => ( currentRow[\"Quantity_Nos\"])) :  currentRow[\"Quantity_Nos\"] })()}}",
      "currencyCode": "USD",
      "decimals": 0,
      "enableFilter": true,
      "enableSort": true,
      "horizontalAlignment": "CENTER",
      "id": "Quantity_Nos",
      "index": 0,
      "isCellEditable": false,
      "isCellVisible": true,
      "isDerived": false,
      "isDisabled": false,
      "isDiscardVisible": true,
      "isEditable": false,
      "isSaveVisible": true,
      "isVisible": true,
      "label": "Quantity_Nos",
      "notation": "standard",
      "originalId": "Quantity_Nos",
      "sticky": "",
      "textSize": "0.875rem",
      "thousandSeparator": true,
      "validation": {},
      "verticalAlignment": "CENTER",
      "width": 150
    },
    "Remarks": {
      "alias": "Remarks",
      "allowCellWrapping": true,
      "allowSameOptionsInNewRow": true,
      "columnType": "text",
      "computedValue": "{{(() => { const tableData = Table1.processedTableData || []; return tableData.length > 0 ? tableData.map((currentRow, currentIndex) => ( currentRow[\"Remarks\"])) :  currentRow[\"Remarks\"] })()}}",
      "currencyCode": "USD",
      "decimals": 0,
      "enableFilter": true,
      "enableSort": true,
      "horizontalAlignment": "CENTER",
      "id": "Remarks",
      "index": 4,
      "isCellEditable": false,
      "isCellVisible": true,
      "isDerived": false,
      "isDisabled": false,
      "isDiscardVisible": true,
      "isEditable": false,
      "isSaveVisible": true,
      "isVisible": true,
      "label": "Remarks",
      "notation": "standard",
      "originalId": "Remarks",
      "sticky": "",
      "textSize": "0.875rem",
      "thousandSeparator": true,
      "validation": {},
      "verticalAlignment": "CENTER",
      "width": 150
    }
  },
  "renderMode": "CANVAS",
  "responsiveBehavior": "fill",
  "rightColumn": 64,
  "searchKey": "",
  "tableData": "{{appsmith.store.selectedItems}}\n",
  "textSize": "0.875rem",
  "topRow": 42,
  "totalRecordsCount": 0,
  "type": "TABLE_WIDGET_V2",
  "version": 2,
  "verticalAlignment": "CENTER",
  "widgetId": "gcf5c1h0ie",
  "widgetName": "Table1"
}