{
  "animateLoading": true,
  "backgroundColor": "#FFFFFF",
  "borderColor": "#E0DEDE",
  "borderRadius": "{{appsmith.theme.borderRadius.appBorderRadius}}",
  "borderWidth": "1",
  "bottomRow": 41,
  "boxShadow": "{{appsmith.theme.boxShadow.appBoxShadow}}",
  "children": [
    {
      "borderRadius": "{{appsmith.theme.borderRadius.appBorderRadius}}",
      "bottomRow": 210,
      "boxShadow": "{{appsmith.theme.boxShadow.appBoxShadow}}",
      "canExtend": false,
      "containerStyle": "none",
      "detachFromLayout": true,
      "dynamicBindingPathList": [
        {
          "key": "borderRadius"
        },
        {
          "key": "boxShadow"
        }
      ],
      "dynamicHeight": "AUTO_HEIGHT",
      "flexLayers": [],
      "isLoading": false,
      "isVisible": true,
      "key": "u8w4o0ch8x",
      "leftColumn": 0,
      "maxDynamicHeight": 9000,
      "minDynamicHeight": 4,
      "minHeight": 400,
      "minWidth": 450,
      "mobileBottomRow": 400,
      "mobileLeftColumn": 0,
      "mobileRightColumn": 485.25,
      "mobileTopRow": 0,
      "needsErrorInfo": false,
      "parentColumnSpace": 1,
      "parentId": "nkpglmt8ry",
      "parentRowSpace": 1,
      "renderMode": "CANVAS",
      "responsiveBehavior": "fill",
      "rightColumn": 485.25,
      "topRow": 0,
      "type": "CANVAS_WIDGET",
      "version": 1,
      "widgetId": "a611023t14",
      "widgetName": "Canvas15"
    }
  ],
  "dynamicBindingPathList": [
    {
      "key": "borderRadius"
    },
    {
      "key": "boxShadow"
    }
  ],
  "dynamicHeight": "FIXED",
  "dynamicTriggerPathList": [],
  "flexVerticalAlignment": "stretch",
  "isCanvas": true,
  "isLoading": false,
  "isVisible": true,
  "key": "1zq9aj3ct9",
  "leftColumn": 2,
  "maxDynamicHeight": 41,
  "minDynamicHeight": 10,
  "minWidth": 450,
  "mobileBottomRow": 64,
  "mobileLeftColumn": 0,
  "mobileRightColumn": 24,
  "mobileTopRow": 24,
  "needsErrorInfo": false,
  "parentColumnSpace": 20.21875,
  "parentId": "0",
  "parentRowSpace": 10,
  "positioning": "fixed",
  "renderMode": "CANVAS",
  "responsiveBehavior": "fill",
  "rightColumn": 55,
  "shouldScrollContents": true,
  "topRow": 20,
  "type": "FORM_WIDGET",
  "widgetId": "nkpglmt8ry",
  "widgetName": "Form1"
}